cnd_scaffold/__init__.py
cnd_scaffold/__version__.py
cnd_scaffold/cnd_scaffold.py
cnd_scaffold/file.py
cnd_scaffold/scaffold.py
cnd_scaffold/structure.py
cnd_scaffold-3.2.1.dist-info/METADATA
cnd_scaffold-3.2.1.dist-info/WHEEL
cnd_scaffold-3.2.1.dist-info/RECORD
