Metadata-Version: 2.1
Name: cnd_scaffold
Version: 3.2.1
Summary: Tools initiate a new project in git lab, based on a existing definition
Author: Denis Fabien <denis@changendevops.com>
Classifier: License :: OSI Approved :: MIT License
Classifier: Operating System :: OS Independent
Classifier: Programming Language :: Python :: 3
Requires-Python: >=3.7
Requires-Dist: cndio
Requires-Dist: cndprint
Requires-Dist: hatch-requirements-txt
Requires-Dist: jinja2
Requires-Dist: pyyaml
Requires-Dist: requests
Requires-Dist: twine
Requires-Dist: yamale
